taskforceai/__init__.py
taskforceai/async_client.py
taskforceai/client.py
taskforceai/exceptions.py
taskforceai/models.py
taskforceai/streams.py
taskforceai/sync_client.py
taskforceai/types.py
taskforceai/utils.py
taskforceai-1.3.1.dist-info/licenses/LICENSE
taskforceai-1.3.1.dist-info/METADATA
taskforceai-1.3.1.dist-info/WHEEL
taskforceai-1.3.1.dist-info/top_level.txt
taskforceai-1.3.1.dist-info/RECORD
