Metadata-Version: 2.4
Name: taskforceai
Version: 1.3.1
Summary: TaskForceAI Python SDK
Author: TaskForceAI
License-Expression: MIT
Project-URL: Homepage, https://taskforceai.chat
Project-URL: Repository, https://github.com/ClayWarren/taskforceai-sdk-python
Project-URL: Issues, https://github.com/ClayWarren/taskforceai-sdk-python/issues
Keywords: ai,multi-agent,sdk,taskforceai
Classifier: Programming Language :: Python
Classifier: Programming Language :: Python :: 3
Classifier: Programming Language :: Python :: 3.9
Classifier: Programming Language :: Python :: 3.10
Classifier: Programming Language :: Python :: 3.11
Classifier: Programming Language :: Python :: 3.12
Classifier: Operating System :: OS Independent
Requires-Python: >=3.9
License-File: LICENSE
Requires-Dist: httpx<0.28,>=0.24
Requires-Dist: pydantic>=2.0
Provides-Extra: dev
Requires-Dist: pytest==9.0.1; extra == "dev"
Requires-Dist: pytest-asyncio==1.3.0; extra == "dev"
Requires-Dist: anyio==4.11.0; extra == "dev"
Requires-Dist: ruff==0.14.5; extra == "dev"
Requires-Dist: mypy==1.18.2; extra == "dev"
Dynamic: license-file
